{
  "id": "algun_proy",
  "title": "Algún proyecto?",
  "content": "<p> Mi mamá pudo haber participado en un campeonato mundial \n              de madres judías con bastantes posibilidades, no sé \n              si de ganarlo pero seguramente de hacer un buen papel.</p>\n<p> A principios del ’90 y al regreso de unas vacaciones, fuimos \n              con mi mujer a tomar un habitual cafecito de los sábados \n              a casa de mi vieja. Nos recibió con el siempre sabroso café \n              “a la turca” y con la acostumbrada exageración \n              de dulces y cosas ricas como para hacer entrar en sobrepeso a un \n              regimiento de gurkas. Luego de un rato de charla se puso un poco \n              seria y me preguntó: “Querido, tenés algún \n              proyecto de trabajo?” Como le contesté que no, se puso \n              más seria y comentó: “Ay, Ernie, estoy un poco \n              preocupada...” Mi rápida respuesta fue: “Dale, \n              vieja, recién estamos en marzo, es principio de temporada, \n              hay algunas puntas por ahí, no te preocupes que algo va a \n              salir, quedate tranquila...” Y mi vieja dale con lo mismo: \n              “Ay, no Ernie, como voy a quedarme tranquila? Es en esto que \n              me quedo pensando todas las noches... a veces ni puedo dormir... \n              estoy muy preocupada...” Entonces Cristina, tratando de “aligerar” \n              el ambiente: “Bueno, Rita, no se preocupe tanto, no es para \n              hacerse tanta malasangre...” Y mi vieja, con su tonito cruza \n              de madre judía de libro y reina en el exilio: “Puede \n              ser... pero lo hago con gusto!”</p>\n<p></p>",
  "category": "General",
  "cleanTitle": "Algún proyecto?"
}