{
  "id": "1971",
  "source": "1971.htm",
  "title": "Opus Pi (1971)",
  "content": "<h1>Les Luthiers</h1>\n<a href=\"index.html\">- \n Comienzo</a><a href=\"espect.html\">- \n Espectáculos</a>\n\n<h2>Opus Pi1971</h2>\n<h5>Teatro IFT, Café-concert La cebolla, Buenos Aires, \n 1971<br>Café del Puerto, Punta del Este, 1972</h5>\n<h5><strong><strong>Chanson de Les Luthiers</strong></h5>\n<h5><strong>Voglio entrare per la finestra</strong></h5>\n<h5><strong>Conozca el interior</strong></h5>\n<h5><strong>Romanza escocesa sin palabras</strong></h5>\n<h5><strong>Manuela’s blues</strong></h5>\n<h5><strong>Pieza en forma de tango</strong></h5>\n<h5><strong>Quinteto de vientos</strong></h5>\n<h5><strong>Bolero de Mastropiero</strong></h5>\n<h5><strong>Oda a la alegría gitana</strong></h5>\n<h5><strong>Suite los Noticiarios Cinematográficos<br></strong></h5>\n<a href=\"discos.html\">- Discografía</a><a href=\"fotos.html\">- Fotos</a><a href=\"videos.html\">- Videos</a>",
  "images": []
}